grakn/__init__.py
grakn/client.py
grakn/exception/GraknError.py
grakn/exception/__init__.py
grakn/rpc/__init__.py
grakn/rpc/protocol/__init__.py
grakn/rpc/protocol/keyspace/Keyspace_pb2.py
grakn/rpc/protocol/keyspace/Keyspace_pb2_grpc.py
grakn/rpc/protocol/keyspace/__init__.py
grakn/rpc/protocol/session/Answer_pb2.py
grakn/rpc/protocol/session/Answer_pb2_grpc.py
grakn/rpc/protocol/session/Concept_pb2.py
grakn/rpc/protocol/session/Concept_pb2_grpc.py
grakn/rpc/protocol/session/Session_pb2.py
grakn/rpc/protocol/session/Session_pb2_grpc.py
grakn/rpc/protocol/session/__init__.py
grakn/service/__init__.py
grakn/service/Keyspace/KeyspaceService.py
grakn/service/Keyspace/__init__.py
grakn/service/Session/TransactionService.py
grakn/service/Session/__init__.py
grakn/service/Session/Concept/BaseTypeMapping.py
grakn/service/Session/Concept/Concept.py
grakn/service/Session/Concept/ConceptFactory.py
grakn/service/Session/Concept/__init__.py
grakn/service/Session/util/RequestBuilder.py
grakn/service/Session/util/ResponseReader.py
grakn/service/Session/util/__init__.py
grakn/service/Session/util/enums.py
grakn_client-1.5.3.dist-info/METADATA
grakn_client-1.5.3.dist-info/WHEEL
grakn_client-1.5.3.dist-info/top_level.txt
grakn_client-1.5.3.dist-info/RECORD
