Metadata-Version: 2.1
Name: grakn-client
Version: 1.5.3
Summary: Grakn Client for Python
Home-page: https://github.com/graknlabs/grakn/tree/master/client-python
Author: Grakn Labs
Author-email: community@grakn.ai
License: Apache-2.0
Keywords: grakn database graph knowledgebase knowledge-engineering
Platform: UNKNOWN
Classifier: Programming Language :: Python
Classifier: Programming Language :: Python :: 2
Classifier: Programming Language :: Python :: 2.7
Classifier: Programming Language :: Python :: 3
Classifier: Programming Language :: Python :: 3.4
Classifier: Programming Language :: Python :: 3.5
Classifier: Programming Language :: Python :: 3.6
Classifier: Programming Language :: Python :: 3.7
Classifier: Programming Language :: Python :: 3.8
Classifier: License :: OSI Approved :: Apache Software License
Classifier: Operating System :: OS Independent
Classifier: Intended Audience :: Developers
Classifier: Intended Audience :: Science/Research
Classifier: Environment :: Console
Classifier: Topic :: Database :: Front-Ends
